py_mono_tools/CONF
py_mono_tools/__init__.py
py_mono_tools/backends/__init__.py
py_mono_tools/backends/docker.py
py_mono_tools/backends/interface.py
py_mono_tools/backends/system.py
py_mono_tools/cli_interface.py
py_mono_tools/config.py
py_mono_tools/goals/__init__.py
py_mono_tools/goals/deployers.py
py_mono_tools/goals/interface.py
py_mono_tools/goals/linters.py
py_mono_tools/goals/testers.py
py_mono_tools/main.py
py_mono_tools/py.typed
py_mono_tools/templates/CONF
py_mono_tools/templates/dockerfiles/main_template.Dockerfile
py_mono_tools/utils.py
py_mono_tools-0.0.38.dist-info/entry_points.txt
py_mono_tools-0.0.38.dist-info/LICENSE
py_mono_tools-0.0.38.dist-info/WHEEL
py_mono_tools-0.0.38.dist-info/METADATA
py_mono_tools-0.0.38.dist-info/RECORD
